asgi_aws/__init__.py
asgi_aws/py.typed
asgi_aws/service.py
asgi_aws/types.py
asgi_aws/services/__init__.py
asgi_aws/services/aws.py
asgi_aws/services/http.py
asgi_aws-2.0.0.dist-info/METADATA
asgi_aws-2.0.0.dist-info/WHEEL
asgi_aws-2.0.0.dist-info/licenses/LICENSE
asgi_aws-2.0.0.dist-info/RECORD
